mxpit/__init__.py
mxpit/image_classification.py
mxpit/object_detection.py
mxpit/sound_classification.py
mxpit/FastDev/__init__.py
mxpit/FastDev/eval.py
mxpit/FastDev/test.py
mxpit/FastDev/train.py
mxpit/FastDev/__pycache__/__init__.cpython-310.pyc
mxpit/FastDev/__pycache__/__init__.cpython-38.pyc
mxpit/FastDev/checkpoint/.gitkeep
mxpit/FastDev/configs/coco.names
mxpit/FastDev/configs/coco.yaml
mxpit/FastDev/example/ncnn/.gitkeep
mxpit/FastDev/example/ncnn/3.jpg
mxpit/FastDev/example/ncnn/FastestDet.bin
mxpit/FastDev/example/ncnn/FastestDet.cpp
mxpit/FastDev/example/ncnn/FastestDet.param
mxpit/FastDev/example/ncnn/build.sh
mxpit/FastDev/example/ncnn/result.jpg
mxpit/FastDev/example/onnx-runtime/runtime.py
mxpit/FastDev/module/custom_layers.py
mxpit/FastDev/module/detector.py
mxpit/FastDev/module/loss.py
mxpit/FastDev/module/shufflenetv2.pth
mxpit/FastDev/module/shufflenetv2.py
mxpit/FastDev/module/__pycache__/custom_layers.cpython-310.pyc
mxpit/FastDev/module/__pycache__/custom_layers.cpython-38.pyc
mxpit/FastDev/module/__pycache__/custom_layers.cpython-39.pyc
mxpit/FastDev/module/__pycache__/detector.cpython-310.pyc
mxpit/FastDev/module/__pycache__/detector.cpython-38.pyc
mxpit/FastDev/module/__pycache__/detector.cpython-39.pyc
mxpit/FastDev/module/__pycache__/loss.cpython-310.pyc
mxpit/FastDev/module/__pycache__/loss.cpython-38.pyc
mxpit/FastDev/module/__pycache__/loss.cpython-39.pyc
mxpit/FastDev/module/__pycache__/shufflenetv2.cpython-310.pyc
mxpit/FastDev/module/__pycache__/shufflenetv2.cpython-38.pyc
mxpit/FastDev/module/__pycache__/shufflenetv2.cpython-39.pyc
mxpit/FastDev/utils/datase.py
mxpit/FastDev/utils/datasets.py
mxpit/FastDev/utils/evaluation.py
mxpit/FastDev/utils/tool.py
mxpit/FastDev/utils/__pycache__/datase.cpython-310.pyc
mxpit/FastDev/utils/__pycache__/datase.cpython-38.pyc
mxpit/FastDev/utils/__pycache__/datasets.cpython-310.pyc
mxpit/FastDev/utils/__pycache__/datasets.cpython-38.pyc
mxpit/FastDev/utils/__pycache__/datasets.cpython-39.pyc
mxpit-1.4.5.dist-info/METADATA
mxpit-1.4.5.dist-info/WHEEL
mxpit-1.4.5.dist-info/top_level.txt
mxpit-1.4.5.dist-info/RECORD
