Metadata-Version: 2.1
Name: mxpit
Version: 1.4.5
Summary: Mxpi-train
Home-page: https://github.com/yuanyunqiang/
Author: YuanYunQiang
Author-email: 649756903@qq.com
License: MIT Licence
Keywords: pip,SICA
Platform: any
Requires-Dist: numpy (<1.24.0)
Requires-Dist: onnx
Requires-Dist: onnx-simplifier
Requires-Dist: onnxruntime
Requires-Dist: onnxsim
Requires-Dist: opencv-python
Requires-Dist: mxpi-pycocotools
Requires-Dist: pycocotools
Requires-Dist: PyYAML
Requires-Dist: torchsummary
Requires-Dist: tqdm
Requires-Dist: pywin32
Requires-Dist: torch
Requires-Dist: torchvision
Requires-Dist: torchaudio
Requires-Dist: future
Requires-Dist: tensorboard
Requires-Dist: neural-compressor
Requires-Dist: ffmpeg
Requires-Dist: resampy
Requires-Dist: soundfile
Requires-Dist: librosa
Requires-Dist: termcolor
Requires-Dist: pyaudio
